{
	"info": {
		"_postman_id": "2b14d071-ddac-495a-bf1d-2c05f86fbb19",
		"name": "DjangoAuthAPI",
		"schema": "https://schema.getpostman.com/json/collection/v2.1.0/collection.json"
	},
	"item": [
		{
			"name": "User Registration",
			"request": {
				"method": "POST",
				"header": [
					{
						"key": "Accept",
						"value": "application/json",
						"type": "text"
					}
				],
				"body": {
					"mode": "raw",
					"raw": "{\r\n    \"email\" : \"alaminbhuyan633@gmail.com\",\r\n    \"name\" : \"alamin\",\r\n    \"password\" : \"1234\",\r\n    \"password2\" : \"1234\",\r\n    \"tc\" : \"True\"\r\n}",
					"options": {
						"raw": {
							"language": "json"
						}
					}
				},
				"url": {
					"raw": "http://127.0.0.1:8000/api/user/register/",
					"protocol": "http",
					"host": [
						"127",
						"0",
						"0",
						"1"
					],
					"port": "8000",
					"path": [
						"api",
						"user",
						"register",
						""
					],
					"query": [
						{
							"key": "",
							"value": null,
							"disabled": true
						}
					]
				}
			},
			"response": []
		},
		{
			"name": "Login User",
			"request": {
				"method": "POST",
				"header": [
					{
						"key": "Accept",
						"value": "application/json",
						"type": "text"
					}
				],
				"body": {
					"mode": "raw",
					"raw": "{\r\n    \"email\" : \"alaminbhuyan633@gmail.com\",\r\n    \"password\" : \"1234\"\r\n}",
					"options": {
						"raw": {
							"language": "json"
						}
					}
				},
				"url": {
					"raw": "http://127.0.0.1:8000/api/user/login/",
					"protocol": "http",
					"host": [
						"127",
						"0",
						"0",
						"1"
					],
					"port": "8000",
					"path": [
						"api",
						"user",
						"login",
						""
					]
				}
			},
			"response": []
		},
		{
			"name": "User Profile",
			"protocolProfileBehavior": {
				"disableBodyPruning": true
			},
			"request": {
				"method": "GET",
				"header": [
					{
						"key": "Accept",
						"value": "application/json",
						"type": "text"
					},
					{
						"key": "Authorization",
						"value": "Bearer eyJ0eXAiOiJKV1QiLCJhbGciOiJIUzI1NiJ9.eyJ0b2tlbl90eXBlIjoiYWNjZXNzIiwiZXhwIjoxNjQ3Mzk5MDExLCJpYXQiOjE2NDczOTg3MTEsImp0aSI6IjEzZmMyN2Y5MWY0MzRmZjI5YTBlNjc3NmU5M2E0ZDlmIiwidXNlcl9pZCI6NH0.CqdLEghHCxgnDqwLRxGnDs6iEFLXqFkvRjGukWo5wsA",
						"type": "text"
					}
				],
				"body": {
					"mode": "raw",
					"raw": "",
					"options": {
						"raw": {
							"language": "json"
						}
					}
				},
				"url": {
					"raw": "http://127.0.0.1:8000/api/user/profile/",
					"protocol": "http",
					"host": [
						"127",
						"0",
						"0",
						"1"
					],
					"port": "8000",
					"path": [
						"api",
						"user",
						"profile",
						""
					],
					"query": [
						{
							"key": "",
							"value": null,
							"disabled": true
						}
					]
				}
			},
			"response": []
		},
		{
			"name": "User Change Password",
			"request": {
				"method": "POST",
				"header": [
					{
						"key": "Accept",
						"value": "application/json",
						"type": "text"
					},
					{
						"key": "Authorization",
						"value": "Bearer eyJ0eXAiOiJKV1QiLCJhbGciOiJIUzI1NiJ9.eyJ0b2tlbl90eXBlIjoiYWNjZXNzIiwiZXhwIjoxNjQ3Mzk5NjkzLCJpYXQiOjE2NDczOTkzOTMsImp0aSI6ImIxMTk4NjlhZGY0NTQ5MTg5MTBjNWM4NWNkMTRhMDUyIiwidXNlcl9pZCI6NH0.HmmSo1uS3VPZO6-l9h-rS1U3k3QCseSqw21s3gZaktg",
						"type": "text"
					}
				],
				"body": {
					"mode": "raw",
					"raw": "{\r\n    \"password\" : \"geekyshows\",\r\n    \"password2\" : \"geekyshows\"\r\n}",
					"options": {
						"raw": {
							"language": "json"
						}
					}
				},
				"url": {
					"raw": "http://127.0.0.1:8000/api/user/changepassword/",
					"protocol": "http",
					"host": [
						"127",
						"0",
						"0",
						"1"
					],
					"port": "8000",
					"path": [
						"api",
						"user",
						"changepassword",
						""
					]
				}
			},
			"response": []
		},
		{
			"name": "Send Password Reset Email",
			"request": {
				"method": "POST",
				"header": [
					{
						"key": "Accept",
						"value": "application/json",
						"type": "text"
					}
				],
				"body": {
					"mode": "raw",
					"raw": "{\r\n    \"email\" : \"alaminbhuyan633@gmail.com\"\r\n}",
					"options": {
						"raw": {
							"language": "json"
						}
					}
				},
				"url": {
					"raw": "http://127.0.0.1:8000/api/user/send-reset-password-email/",
					"protocol": "http",
					"host": [
						"127",
						"0",
						"0",
						"1"
					],
					"port": "8000",
					"path": [
						"api",
						"user",
						"send-reset-password-email",
						""
					]
				}
			},
			"response": []
		},
		{
			"name": "Reset User Password",
			"request": {
				"method": "POST",
				"header": [
					{
						"key": "Accept",
						"value": "application/json",
						"type": "text"
					}
				],
				"body": {
					"mode": "raw",
					"raw": "{\r\n    \"password\" : \"12345\",\r\n    \"password2\" : \"12345\"\r\n}",
					"options": {
						"raw": {
							"language": "json"
						}
					}
				},
				"url": {
					"raw": "http://127.0.0.1:8000/api/user/reset-password/NQ/b2di5d-d0b80e2e3f30ebd7979e416e7e030edb/",
					"protocol": "http",
					"host": [
						"127",
						"0",
						"0",
						"1"
					],
					"port": "8000",
					"path": [
						"api",
						"user",
						"reset-password",
						"NQ",
						"b2di5d-d0b80e2e3f30ebd7979e416e7e030edb",
						""
					]
				}
			},
			"response": []
		}
	]
}